mecab_ko_dic/__init__.py
mecab_ko_dic/dictionary/char.bin
mecab_ko_dic/dictionary/dicrc
mecab_ko_dic/dictionary/feature.def
mecab_ko_dic/dictionary/left-id.def
mecab_ko_dic/dictionary/matrix.bin
mecab_ko_dic/dictionary/model.bin
mecab_ko_dic/dictionary/pos-id.def
mecab_ko_dic/dictionary/rewrite.def
mecab_ko_dic/dictionary/right-id.def
mecab_ko_dic/dictionary/sys.dic
mecab_ko_dic/dictionary/unk.dic
python_mecab_ko_dic-2.1.1.post1.dist-info/LICENSE
python_mecab_ko_dic-2.1.1.post1.dist-info/METADATA
python_mecab_ko_dic-2.1.1.post1.dist-info/WHEEL
python_mecab_ko_dic-2.1.1.post1.dist-info/top_level.txt
python_mecab_ko_dic-2.1.1.post1.dist-info/RECORD
