Metadata-Version: 2.1
Name: python-mecab-ko-dic
Version: 2.1.1.post1
Summary: mecab-ko-dic packaged for Python
Home-page: https://github.com/jonghwanhyeon/python-mecab-ko-dic
Author: Jonghwan Hyeon
Author-email: jonghwanhyeon93@gmail.com
License: Apache License 2.0
Keywords: mecab,mecab-ko,mecab-dic
Classifier: Intended Audience :: Science/Research
Classifier: License :: OSI Approved :: Apache Software License
Classifier: Natural Language :: Korean
Classifier: Operating System :: OS Independent
Classifier: Programming Language :: Python :: 3
Classifier: Programming Language :: Python :: 3 :: Only
Classifier: Topic :: Text Processing
Classifier: Topic :: Text Processing :: Linguistic
License-File: LICENSE
